gitelle/__init__.py
gitelle/cli.py
gitelle/commands/__init__.py
gitelle/commands/add.py
gitelle/commands/branch.py
gitelle/commands/checkout.py
gitelle/commands/clone.py
gitelle/commands/commit.py
gitelle/commands/diff.py
gitelle/commands/init.py
gitelle/commands/log.py
gitelle/commands/reset.py
gitelle/commands/status.py
gitelle/core/__init__.py
gitelle/core/index.py
gitelle/core/objects.py
gitelle/core/refs.py
gitelle/core/repository.py
gitelle/utils/__init__.py
gitelle/utils/compression.py
gitelle/utils/config.py
gitelle/utils/diff.py
gitelle/utils/filesystem.py
gitelle/utils/hashing.py
gitelle-0.2.0.dist-info/LICENSE
gitelle-0.2.0.dist-info/METADATA
gitelle-0.2.0.dist-info/WHEEL
gitelle-0.2.0.dist-info/entry_points.txt
gitelle-0.2.0.dist-info/top_level.txt
gitelle-0.2.0.dist-info/RECORD
