Metadata-Version: 2.2
Name: gitelle
Version: 0.2.0
Summary: A lightweight, educational implementation of Git in Python
Home-page: https://github.com/EllE961/gitelle
Author: EllE961
Author-email: EllE961 <yahyaalsalmi961@gmail.com>
License: MIT License
Project-URL: Homepage, https://github.com/EllE961/gitelle
Project-URL: Bug Tracker, https://github.com/EllE961/gitelle/issues
Project-URL: Documentation, https://gitelle.readthedocs.io/
Classifier: Programming Language :: Python :: 3
Classifier: Programming Language :: Python :: 3.8
Classifier: Programming Language :: Python :: 3.9
Classifier: Programming Language :: Python :: 3.10
Classifier: Programming Language :: Python :: 3.11
Classifier: License :: OSI Approved :: MIT License
Classifier: Operating System :: OS Independent
Classifier: Development Status :: 3 - Alpha
Classifier: Intended Audience :: Developers
Classifier: Intended Audience :: Education
Classifier: Topic :: Software Development :: Version Control :: Git
Requires-Python: >=3.8
License-File: LICENSE
Requires-Dist: click>=8.0.0
Requires-Dist: zlib-wrapper>=0.1.3
Requires-Dist: pathlib>=1.0.1
Requires-Dist: pyyaml>=6.0
Dynamic: author
Dynamic: home-page
Dynamic: requires-python
